{
    "Version": "1.2",
    "Data": {
        "Source": "i:\\unreal\\projectds\\projectds\\intermediate\\build\\win64\\unrealeditor\\inc\\projectds\\uht\\maingamepc.gen.cpp",
        "ProvidedModule": "",
        "PCH": "i:\\unreal\\projectds\\projectds\\intermediate\\build\\win64\\x64\\projectdseditor\\development\\unrealed\\sharedpch.unrealed.project.valapi.cpp20.h.pch",
        "Includes": [
            "i:\\unreal\\projectds\\projectds\\intermediate\\build\\win64\\x64\\unrealeditor\\development\\projectds\\definitions.projectds.h",
            "i:\\unreal\\projectds\\projectds\\source\\projectds\\public\\controller\\maingamepc.h",
            "i:\\unreal\\projectds\\projectds\\intermediate\\build\\win64\\unrealeditor\\inc\\projectds\\uht\\maingamepc.generated.h"
        ],
        "ImportedModules": [],
        "ImportedHeaderUnits": []
    }
}